nltk_tools/__init__.py
nltk_tools/programs.py
nltktrans-0.1.0.dist-info/LICENSE
nltktrans-0.1.0.dist-info/METADATA
nltktrans-0.1.0.dist-info/WHEEL
nltktrans-0.1.0.dist-info/top_level.txt
nltktrans-0.1.0.dist-info/RECORD
