Metadata-Version: 2.2
Name: nltktrans
Version: 0.1.0
Summary: NLTK transformation package with tokenization, POS tagging, and TF-IDF functions
Home-page: https://github.com/krishaga/nltk_tools
Author: NageGowda from Karnataka
Author-email: akkirat2016@gmail.com
Classifier: Programming Language :: Python :: 3
Classifier: License :: OSI Approved :: MIT License
Classifier: Operating System :: OS Independent
Requires-Python: >=3.6
License-File: LICENSE
Requires-Dist: nltk>=3.6
Requires-Dist: pandas>=1.3
Requires-Dist: numpy>=1.21
Requires-Dist: scikit-learn>=1.0
Dynamic: author
Dynamic: author-email
Dynamic: classifier
Dynamic: description
Dynamic: description-content-type
Dynamic: home-page
Dynamic: requires-dist
Dynamic: requires-python
Dynamic: summary
